openapi_generator.py
couchdb_openapi_scheme_generator-1.1.0.dist-info/METADATA
couchdb_openapi_scheme_generator-1.1.0.dist-info/WHEEL
couchdb_openapi_scheme_generator-1.1.0.dist-info/entry_points.txt
couchdb_openapi_scheme_generator-1.1.0.dist-info/licenses/LICENSE
couchdb_openapi_scheme_generator-1.1.0.dist-info/RECORD
