Metadata-Version: 2.4
Name: couchdb-openapi-scheme-generator
Version: 1.1.0
Summary: CouchDB OpenAPI scheme generator
Project-URL: Homepage, https://github.com/SasukeSagara/CouchDB-OpenAPI-scheme-generator
Project-URL: Repository, https://github.com/SasukeSagara/CouchDB-OpenAPI-scheme-generator
Project-URL: Issues, https://github.com/SasukeSagara/CouchDB-OpenAPI-scheme-generator/issues
Author: CouchDB OpenAPI scheme generator contributors
License: MIT
License-File: LICENSE
Keywords: api,couchdb,generator,openapi,specification,swagger
Classifier: Development Status :: 4 - Beta
Classifier: Intended Audience :: Developers
Classifier: License :: OSI Approved :: MIT License
Classifier: Programming Language :: Python :: 3
Classifier: Programming Language :: Python :: 3.11
Classifier: Programming Language :: Python :: 3.12
Classifier: Programming Language :: Python :: 3.13
Classifier: Topic :: Database
Classifier: Topic :: Internet :: WWW/HTTP :: HTTP Servers
Classifier: Topic :: Software Development :: Libraries :: Python Modules
Requires-Python: >=3.11
Requires-Dist: pyyaml>=6.0.2
Requires-Dist: requests>=2.32.5
